[{"name":"metadata.json","path":"dist/metadata.json","internal_type":35,"type":"Metadata"},{"name":"baastream-scan","path":"dist/baastream-scan_darwin_arm64_v8.0/baastream-scan","goos":"darwin","goarch":"arm64","goarm64":"v8.0","target":"darwin_arm64_v8.0","internal_type":4,"type":"Binary","extra":{"Binary":"baastream-scan","Builder":"go","Ext":"","ID":"baastream-scan"}},{"name":"baastream-scan.exe","path":"dist/baastream-scan_windows_arm64_v8.0/baastream-scan.exe","goos":"windows","goarch":"arm64","goarm64":"v8.0","target":"windows_arm64_v8.0","internal_type":4,"type":"Binary","extra":{"Binary":"baastream-scan","Builder":"go","Ext":".exe","ID":"baastream-scan"}},{"name":"baastream-scan","path":"dist/baastream-scan_linux_arm64_v8.0/baastream-scan","goos":"linux","goarch":"arm64","goarm64":"v8.0","target":"linux_arm64_v8.0","internal_type":4,"type":"Binary","extra":{"Binary":"baastream-scan","Builder":"go","Ext":"","ID":"baastream-scan"}},{"name":"baastream-scan","path":"dist/baastream-scan_linux_amd64_v1/baastream-scan","goos":"linux","goarch":"amd64","goamd64":"v1","target":"linux_amd64_v1","internal_type":4,"type":"Binary","extra":{"Binary":"baastream-scan","Builder":"go","Ext":"","ID":"baastream-scan"}},{"name":"baastream-scan.exe","path":"dist/baastream-scan_windows_amd64_v1/baastream-scan.exe","goos":"windows","goarch":"amd64","goamd64":"v1","target":"windows_amd64_v1","internal_type":4,"type":"Binary","extra":{"Binary":"baastream-scan","Builder":"go","Ext":".exe","ID":"baastream-scan"}},{"name":"baastream-scan","path":"dist/baastream-scan_darwin_amd64_v1/baastream-scan","goos":"darwin","goarch":"amd64","goamd64":"v1","target":"darwin_amd64_v1","internal_type":4,"type":"Binary","extra":{"Binary":"baastream-scan","Builder":"go","Ext":"","ID":"baastream-scan"}},{"name":"baastream-scan-0.1.1-windows-arm64.zip","path":"dist/baastream-scan-0.1.1-windows-arm64.zip","goos":"windows","goarch":"arm64","goarm64":"v8.0","target":"windows_arm64_v8.0","internal_type":1,"type":"Archive","extra":{"Binaries":["baastream-scan.exe"],"Checksum":"sha256:75091083f681d75c68acbc2f048a089094002692dc4a9b5895b005ed15395b64","Files":["LICENSE","README.md"],"Format":"zip","ID":"default","WrappedIn":""}},{"name":"baastream-scan-0.1.1-darwin-arm64.tar.gz","path":"dist/baastream-scan-0.1.1-darwin-arm64.tar.gz","goos":"darwin","goarch":"arm64","goarm64":"v8.0","target":"darwin_arm64_v8.0","internal_type":1,"type":"Archive","extra":{"Binaries":["baastream-scan"],"Checksum":"sha256:92149da8675b59a6f1cfe1df4814dc1db2c3d165ec5b6faf595b7b588d467f63","Files":["LICENSE","README.md"],"Format":"tar.gz","ID":"default","WrappedIn":""}},{"name":"baastream-scan-0.1.1-windows-amd64.zip","path":"dist/baastream-scan-0.1.1-windows-amd64.zip","goos":"windows","goarch":"amd64","goamd64":"v1","target":"windows_amd64_v1","internal_type":1,"type":"Archive","extra":{"Binaries":["baastream-scan.exe"],"Checksum":"sha256:fe25afc9de08fb2b621032760f56968f74709f35ce718fde3a5bf2cdcfa3a2ec","Files":["LICENSE","README.md"],"Format":"zip","ID":"default","WrappedIn":""}},{"name":"baastream-scan-0.1.1-linux-arm64.tar.gz","path":"dist/baastream-scan-0.1.1-linux-arm64.tar.gz","goos":"linux","goarch":"arm64","goarm64":"v8.0","target":"linux_arm64_v8.0","internal_type":1,"type":"Archive","extra":{"Binaries":["baastream-scan"],"Checksum":"sha256:3c2ae28997db1e74a1f7a9b30865d94ee0ca50f9bfc0a135c3547d2fd44ca168","Files":["LICENSE","README.md"],"Format":"tar.gz","ID":"default","WrappedIn":""}},{"name":"baastream-scan-0.1.1-darwin-amd64.tar.gz","path":"dist/baastream-scan-0.1.1-darwin-amd64.tar.gz","goos":"darwin","goarch":"amd64","goamd64":"v1","target":"darwin_amd64_v1","internal_type":1,"type":"Archive","extra":{"Binaries":["baastream-scan"],"Checksum":"sha256:c2fd2df33dade9adc9cb8c9ea747326302d866f460090b6629999a4a03f4017e","Files":["LICENSE","README.md"],"Format":"tar.gz","ID":"default","WrappedIn":""}},{"name":"baastream-scan-0.1.1-linux-amd64.tar.gz","path":"dist/baastream-scan-0.1.1-linux-amd64.tar.gz","goos":"linux","goarch":"amd64","goamd64":"v1","target":"linux_amd64_v1","internal_type":1,"type":"Archive","extra":{"Binaries":["baastream-scan"],"Checksum":"sha256:5e4e543bf3fd8a95b509e13e0cf54b6ee8e064497f9b15c558f7900f76897692","Files":["LICENSE","README.md"],"Format":"tar.gz","ID":"default","WrappedIn":""}},{"name":"checksums.txt","path":"dist/checksums.txt","internal_type":12,"type":"Checksum","extra":{}}]